{
  "light": {
    "background": "#F0FDF4",
    "foreground": "#14532D",
    "card": "#FFFFFF",
    "cardForeground": "#14532D",
    "sheet": "#FFFFFF",
    "sheetForeground": "#14532D",
    "primary": "#16A34A",
    "primaryForeground": "#FFFFFF",
    "secondary": "#DCFCE7",
    "secondaryForeground": "#15803D",
    "muted": "#F0FDF4",
    "mutedForeground": "#64748B",
    "accent": "#4ADE80",
    "accentForeground": "#14532D",
    "destructive": "#DC2626",
    "destructiveForeground": "#FFFFFF",
    "border": "#BBF7D0",
    "input": "#DCFCE7",
    "focus": "#16A34A",
    "warning": "#F59E0B",
    "warningForeground": "#FFFFFF",
    "success": "#10B981",
    "successForeground": "#FFFFFF",
    "chart1": "#16A34A",
    "chart2": "#4ADE80",
    "chart3": "#86EFAC",
    "chart4": "#15803D",
    "chart5": "#166534"
  },
  "dark": {
    "background": "#14532D",
    "foreground": "#F0FDF4",
    "card": "#166534",
    "cardForeground": "#F0FDF4",
    "sheet": "#15803D",
    "sheetForeground": "#F0FDF4",
    "primary": "#4ADE80",
    "primaryForeground": "#14532D",
    "secondary": "#15803D",
    "secondaryForeground": "#DCFCE7",
    "muted": "#166534",
    "mutedForeground": "#94A3B8",
    "accent": "#16A34A",
    "accentForeground": "#F0FDF4",
    "destructive": "#EF4444",
    "destructiveForeground": "#FFFFFF",
    "border": "#15803D",
    "input": "#166534",
    "focus": "#4ADE80",
    "warning": "#FBBF24",
    "warningForeground": "#14532D",
    "success": "#34D399",
    "successForeground": "#14532D",
    "chart1": "#4ADE80",
    "chart2": "#86EFAC",
    "chart3": "#16A34A",
    "chart4": "#BBF7D0",
    "chart5": "#15803D"
  }
}
