{
  "light": {
    "background": "#FFF7ED",
    "foreground": "#7C2D12",
    "card": "#FFFFFF",
    "cardForeground": "#7C2D12",
    "sheet": "#FFFFFF",
    "sheetForeground": "#7C2D12",
    "primary": "#EA580C",
    "primaryForeground": "#FFFFFF",
    "secondary": "#FFEDD5",
    "secondaryForeground": "#C2410C",
    "muted": "#FFF7ED",
    "mutedForeground": "#64748B",
    "accent": "#FB923C",
    "accentForeground": "#7C2D12",
    "destructive": "#DC2626",
    "destructiveForeground": "#FFFFFF",
    "border": "#FED7AA",
    "input": "#FFEDD5",
    "focus": "#EA580C",
    "warning": "#F59E0B",
    "warningForeground": "#FFFFFF",
    "success": "#10B981",
    "successForeground": "#FFFFFF",
    "chart1": "#EA580C",
    "chart2": "#FB923C",
    "chart3": "#FDBA74",
    "chart4": "#C2410C",
    "chart5": "#9A3412",
    "text": "#7C2D12",
    "textSecondary": "#475569",
    "textMuted": "#64748B"
  },
  "dark": {
    "background": "#7C2D12",
    "foreground": "#FFF7ED",
    "card": "#9A3412",
    "cardForeground": "#FFF7ED",
    "sheet": "#C2410C",
    "sheetForeground": "#FFF7ED",
    "primary": "#FB923C",
    "primaryForeground": "#7C2D12",
    "secondary": "#C2410C",
    "secondaryForeground": "#FFEDD5",
    "muted": "#9A3412",
    "mutedForeground": "#94A3B8",
    "accent": "#EA580C",
    "accentForeground": "#FFF7ED",
    "destructive": "#EF4444",
    "destructiveForeground": "#FFFFFF",
    "border": "#C2410C",
    "input": "#9A3412",
    "focus": "#FB923C",
    "warning": "#FBBF24",
    "warningForeground": "#7C2D12",
    "success": "#34D399",
    "successForeground": "#7C2D12",
    "chart1": "#FB923C",
    "chart2": "#FDBA74",
    "chart3": "#EA580C",
    "chart4": "#FED7AA",
    "chart5": "#C2410C",
    "text": "#FFF7ED",
    "textSecondary": "#CBD5E1",
    "textMuted": "#94A3B8"
  }
}
